{
  "quizId": "06-trainability-theory-quiz",
  "title": "Quiz: Trainability Theory",
  "description": "Test your understanding of the theoretical foundations of trainability",
  "timeLimit": 12,
  "passingScore": 70,
  "totalPoints": 100,
  "questions": [
    {
      "id": "q1",
      "type": "multiple-choice",
      "points": 13,
      "question": "What is the Dynamical Lie Algebra (DLA) of a quantum circuit?",
      "options": [
        {"id": "a", "text": "The set of all possible output states"},
        {"id": "b", "text": "The algebra generated by gate generators and their commutators"},
        {"id": "c", "text": "The classical algebra of circuit parameters"},
        {"id": "d", "text": "The measurement operator algebra"}
      ],
      "correctAnswer": "b",
      "explanation": "The DLA is the smallest Lie algebra containing the gate generators, formed by taking all nested commutators. Its dimension determines circuit expressibility."
    },
    {
      "id": "q2",
      "type": "multiple-choice",
      "points": 13,
      "question": "What does it mean for a circuit ensemble to form a 2-design?",
      "options": [
        {"id": "a", "text": "It has exactly 2 layers"},
        {"id": "b", "text": "Its first two statistical moments match Haar-random unitaries"},
        {"id": "c", "text": "It uses 2-qubit gates only"},
        {"id": "d", "text": "It has 2 free parameters"}
      ],
      "correctAnswer": "b",
      "explanation": "A 2-design is an ensemble whose first and second moments (averages of U⊗U* terms) match those of Haar-random unitaries."
    },
    {
      "id": "q3",
      "type": "multiple-choice",
      "points": 12,
      "question": "According to Levy's Lemma, how do Lipschitz functions concentrate on high-dimensional spheres?",
      "options": [
        {"id": "a", "text": "They don't concentrate at all"},
        {"id": "b", "text": "Polynomially with dimension"},
        {"id": "c", "text": "Exponentially with dimension"},
        {"id": "d", "text": "Logarithmically with dimension"}
      ],
      "correctAnswer": "c",
      "explanation": "Levy's Lemma shows that Lipschitz functions on high-dimensional spheres concentrate exponentially around their mean, with probability of deviation decaying as exp(-cd)."
    },
    {
      "id": "q4",
      "type": "true-false",
      "points": 12,
      "question": "A circuit with polynomial DLA dimension necessarily avoids barren plateaus.",
      "options": [
        {"id": "true", "text": "True"},
        {"id": "false", "text": "False"}
      ],
      "correctAnswer": "false",
      "explanation": "While polynomial DLA dimension is necessary for avoiding expressibility-induced barren plateaus, other factors like cost function locality and initialization also matter."
    },
    {
      "id": "q5",
      "type": "multiple-choice",
      "points": 12,
      "question": "For a global cost function with a circuit forming a 2-design, how does gradient variance scale?",
      "options": [
        {"id": "a", "text": "O(1) - constant"},
        {"id": "b", "text": "O(1/n) - inverse linear"},
        {"id": "c", "text": "O(1/d) where d=2^n"},
        {"id": "d", "text": "O(1/d³) where d=2^n"}
      ],
      "correctAnswer": "d",
      "explanation": "For 2-design circuits with global cost, Var[∂C/∂θ] ~ O(1/d³) = O(2^{-3n}), showing severe exponential suppression."
    },
    {
      "id": "q6",
      "type": "multiple-choice",
      "points": 12,
      "question": "What is the dimension of su(d) for d-dimensional Hilbert space?",
      "options": [
        {"id": "a", "text": "d"},
        {"id": "b", "text": "d²"},
        {"id": "c", "text": "d² - 1"},
        {"id": "d", "text": "2^d"}
      ],
      "correctAnswer": "c",
      "explanation": "The special unitary algebra su(d) has dimension d² - 1 (traceless Hermitian matrices). This is the maximum DLA dimension."
    },
    {
      "id": "q7",
      "type": "multiple-choice",
      "points": 13,
      "question": "How does the variance bound change for a k-local cost function?",
      "options": [
        {"id": "a", "text": "It becomes O(2^k/d), exponentially better for small k"},
        {"id": "b", "text": "It stays the same as global"},
        {"id": "c", "text": "It becomes worse"},
        {"id": "d", "text": "It becomes exactly zero"}
      ],
      "correctAnswer": "a",
      "explanation": "For k-local cost functions, the variance scales as O(2^k/d), which is exponentially better than global (O(1/d³)) when k is small."
    },
    {
      "id": "q8",
      "type": "multiple-select",
      "points": 13,
      "question": "Which conditions together can guarantee trainability? (Select all that apply)",
      "options": [
        {"id": "a", "text": "Polynomial DLA dimension"},
        {"id": "b", "text": "Local cost functions"},
        {"id": "c", "text": "Identity initialization"},
        {"id": "d", "text": "Maximum circuit depth"}
      ],
      "correctAnswer": ["a", "b", "c"],
      "explanation": "Polynomial DLA (a), local costs (b), and identity initialization (c) together help ensure trainability. Maximum depth (d) would worsen barren plateaus."
    }
  ]
}
