{
  "id": "05-crosstalk-characterization",
  "title": "Crosstalk Characterization: ZZ Coupling and Simultaneous Operations",
  "description": "Learn methods for detecting and quantifying crosstalk between qubits, including ZZ coupling measurement, simultaneous randomized benchmarking, and addressability characterization.",
  "order": 5,
  "estimatedMinutes": 45,
  "difficulty": "advanced",
  "prerequisites": [
    "randomized-benchmarking",
    "two-qubit-gates",
    "transmon-qubits"
  ],
  "learningObjectives": [
    "Understand the physical sources of crosstalk in multi-qubit systems",
    "Measure ZZ coupling strength between qubits",
    "Use simultaneous RB to detect operational crosstalk",
    "Characterize addressability and frequency crowding effects",
    "Implement mitigation strategies for crosstalk"
  ],
  "tags": [
    "crosstalk",
    "ZZ-coupling",
    "simultaneous-RB",
    "addressability",
    "frequency-collision",
    "multi-qubit"
  ],
  "hasQuiz": true,
  "hasExercises": true
}
