{
  "exercisesId": "01-adapt-vqe-exercises",
  "title": "Exercises: ADAPT-VQE",
  "description": "Practice implementing and analyzing ADAPT-VQE components",
  "totalPoints": 100,
  "exercises": [
    {
      "id": "ex1",
      "title": "Gradient Computation",
      "type": "coding",
      "difficulty": "intermediate",
      "points": 25,
      "description": "Implement a function to compute the ADAPT-VQE gradient for a given operator. The gradient is the expectation value of the commutator [H, A] with respect to the current state.",
      "starterCode": "import numpy as np\n\ndef compute_adapt_gradient(hamiltonian, operator, state):\n    \"\"\"\n    Compute the ADAPT-VQE gradient for a candidate operator.\n    \n    The gradient is: ⟨ψ|[H, A]|ψ⟩ where [H,A] = HA - AH\n    \n    Args:\n        hamiltonian: numpy array, the system Hamiltonian\n        operator: numpy array, the candidate operator A\n        state: numpy array, the current quantum state |ψ⟩\n    \n    Returns:\n        float: The gradient value (real part of the expectation)\n    \"\"\"\n    # Your code here\n    pass\n\n# Test\nH = np.array([[1, 0, 0, 0],\n              [0, 0, 1, 0],\n              [0, 1, 0, 0],\n              [0, 0, 0, -1]], dtype=complex)\n\nA = np.array([[0, 0, 0, 1],\n              [0, 0, -1, 0],\n              [0, 1, 0, 0],\n              [-1, 0, 0, 0]], dtype=complex)\n\npsi = np.array([1, 0, 0, 0], dtype=complex)  # |00⟩ state\n\ngrad = compute_adapt_gradient(H, A, psi)\nprint(f\"Gradient: {grad}\")",
      "solution": "import numpy as np\n\ndef compute_adapt_gradient(hamiltonian, operator, state):\n    \"\"\"\n    Compute the ADAPT-VQE gradient for a candidate operator.\n    \n    The gradient is: ⟨ψ|[H, A]|ψ⟩ where [H,A] = HA - AH\n    \n    Args:\n        hamiltonian: numpy array, the system Hamiltonian\n        operator: numpy array, the candidate operator A\n        state: numpy array, the current quantum state |ψ⟩\n    \n    Returns:\n        float: The gradient value (real part of the expectation)\n    \"\"\"\n    # Compute commutator [H, A] = H·A - A·H\n    commutator = hamiltonian @ operator - operator @ hamiltonian\n    \n    # Compute expectation value ⟨ψ|[H,A]|ψ⟩\n    expectation = state.conj().T @ commutator @ state\n    \n    # Return real part (should be real for anti-Hermitian A)\n    return np.real(expectation)\n\n# Test\nH = np.array([[1, 0, 0, 0],\n              [0, 0, 1, 0],\n              [0, 1, 0, 0],\n              [0, 0, 0, -1]], dtype=complex)\n\nA = np.array([[0, 0, 0, 1],\n              [0, 0, -1, 0],\n              [0, 1, 0, 0],\n              [-1, 0, 0, 0]], dtype=complex)\n\npsi = np.array([1, 0, 0, 0], dtype=complex)\n\ngrad = compute_adapt_gradient(H, A, psi)\nprint(f\"Gradient: {grad}\")\nprint(f\"Expected: 2.0 (for this example)\")",
      "hints": [
        "The commutator [H, A] = H @ A - A @ H",
        "Use matrix multiplication with @ operator",
        "The expectation is ψ† @ commutator @ ψ",
        "Use np.real() to extract the real part"
      ],
      "testCases": [
        {
          "input": "H=[[1,0],[0,-1]], A=[[0,1],[-1,0]], psi=[1,0]",
          "expected": "2.0"
        }
      ]
    },
    {
      "id": "ex2",
      "title": "Operator Pool Generation",
      "type": "coding",
      "difficulty": "intermediate",
      "points": 25,
      "description": "Generate a Qubit-ADAPT operator pool for an n-qubit system. Include single-qubit Y operators and two-qubit YX, XY combinations.",
      "starterCode": "import numpy as np\nfrom itertools import combinations\n\ndef generate_qubit_adapt_pool(n_qubits):\n    \"\"\"\n    Generate Qubit-ADAPT operator pool matrices.\n    \n    Args:\n        n_qubits: Number of qubits in the system\n    \n    Returns:\n        List of (2^n × 2^n) numpy arrays representing pool operators\n    \"\"\"\n    # Pauli matrices\n    I = np.eye(2, dtype=complex)\n    X = np.array([[0, 1], [1, 0]], dtype=complex)\n    Y = np.array([[0, -1j], [1j, 0]], dtype=complex)\n    Z = np.array([[1, 0], [0, -1]], dtype=complex)\n    \n    def kron_list(matrices):\n        \"\"\"Compute tensor product of list of matrices.\"\"\"\n        result = matrices[0]\n        for m in matrices[1:]:\n            result = np.kron(result, m)\n        return result\n    \n    pool = []\n    \n    # Your code here: Add single-qubit Y operators\n    # Your code here: Add two-qubit YX and XY operators\n    \n    return pool\n\n# Test\npool = generate_qubit_adapt_pool(3)\nprint(f\"Pool size for 3 qubits: {len(pool)}\")\nprint(f\"Expected: 3 (single Y) + 6 (YX pairs) + 6 (XY pairs) = 15\")",
      "solution": "import numpy as np\nfrom itertools import combinations\n\ndef generate_qubit_adapt_pool(n_qubits):\n    \"\"\"\n    Generate Qubit-ADAPT operator pool matrices.\n    \n    Args:\n        n_qubits: Number of qubits in the system\n    \n    Returns:\n        List of (2^n × 2^n) numpy arrays representing pool operators\n    \"\"\"\n    # Pauli matrices\n    I = np.eye(2, dtype=complex)\n    X = np.array([[0, 1], [1, 0]], dtype=complex)\n    Y = np.array([[0, -1j], [1j, 0]], dtype=complex)\n    Z = np.array([[1, 0], [0, -1]], dtype=complex)\n    \n    def kron_list(matrices):\n        \"\"\"Compute tensor product of list of matrices.\"\"\"\n        result = matrices[0]\n        for m in matrices[1:]:\n            result = np.kron(result, m)\n        return result\n    \n    pool = []\n    \n    # Single-qubit Y operators: Y_i\n    for i in range(n_qubits):\n        ops = [I] * n_qubits\n        ops[i] = Y\n        pool.append(kron_list(ops))\n    \n    # Two-qubit operators: Y_i X_j and X_i Y_j\n    for i, j in combinations(range(n_qubits), 2):\n        # Y_i X_j\n        ops_yx = [I] * n_qubits\n        ops_yx[i] = Y\n        ops_yx[j] = X\n        pool.append(kron_list(ops_yx))\n        \n        # X_i Y_j\n        ops_xy = [I] * n_qubits\n        ops_xy[i] = X\n        ops_xy[j] = Y\n        pool.append(kron_list(ops_xy))\n    \n    return pool\n\n# Test\npool = generate_qubit_adapt_pool(3)\nprint(f\"Pool size for 3 qubits: {len(pool)}\")\nprint(f\"Each operator shape: {pool[0].shape}\")\n\n# Verify operators are anti-Hermitian (for generating unitaries)\nfor i, op in enumerate(pool[:3]):\n    is_anti_herm = np.allclose(op, -op.conj().T)\n    print(f\"Operator {i} anti-Hermitian: {is_anti_herm}\")",
      "hints": [
        "Use np.kron() for tensor products",
        "Single Y operators: place Y at position i, I elsewhere",
        "Use itertools.combinations for qubit pairs",
        "Pool should have n + 2*C(n,2) = n + n(n-1) operators"
      ],
      "testCases": [
        {
          "input": "n_qubits=2",
          "expected": "Pool size: 4 (2 single Y + 2 two-qubit)"
        },
        {
          "input": "n_qubits=4",
          "expected": "Pool size: 16 (4 single Y + 12 two-qubit)"
        }
      ]
    },
    {
      "id": "ex3",
      "title": "Operator Selection",
      "type": "coding",
      "difficulty": "advanced",
      "points": 25,
      "description": "Implement the operator selection step of ADAPT-VQE: compute gradients for all pool operators and return the index and gradient of the best operator.",
      "starterCode": "import numpy as np\n\ndef select_best_operator(hamiltonian, pool, state):\n    \"\"\"\n    Select the operator with maximum gradient magnitude.\n    \n    Args:\n        hamiltonian: System Hamiltonian matrix\n        pool: List of operator matrices\n        state: Current quantum state vector\n    \n    Returns:\n        tuple: (best_index, max_gradient, all_gradients)\n    \"\"\"\n    # Your code here\n    pass\n\n# Test with simple 2-qubit system\nI = np.eye(2, dtype=complex)\nX = np.array([[0, 1], [1, 0]], dtype=complex)\nY = np.array([[0, -1j], [1j, 0]], dtype=complex)\nZ = np.array([[1, 0], [0, -1]], dtype=complex)\n\n# Simple Hamiltonian: H = Z⊗I + I⊗Z + 0.5*X⊗X\nH = np.kron(Z, I) + np.kron(I, Z) + 0.5 * np.kron(X, X)\n\n# Pool: Y⊗I, I⊗Y, Y⊗X, X⊗Y\npool = [\n    np.kron(Y, I),\n    np.kron(I, Y),\n    np.kron(Y, X),\n    np.kron(X, Y)\n]\n\n# Initial state |00⟩\npsi = np.array([1, 0, 0, 0], dtype=complex)\n\nbest_idx, max_grad, grads = select_best_operator(H, pool, psi)\nprint(f\"Best operator index: {best_idx}\")\nprint(f\"Maximum gradient: {max_grad:.4f}\")\nprint(f\"All gradients: {[f'{g:.4f}' for g in grads]}\")",
      "solution": "import numpy as np\n\ndef select_best_operator(hamiltonian, pool, state):\n    \"\"\"\n    Select the operator with maximum gradient magnitude.\n    \n    Args:\n        hamiltonian: System Hamiltonian matrix\n        pool: List of operator matrices\n        state: Current quantum state vector\n    \n    Returns:\n        tuple: (best_index, max_gradient, all_gradients)\n    \"\"\"\n    gradients = []\n    \n    for operator in pool:\n        # Compute commutator [H, A]\n        commutator = hamiltonian @ operator - operator @ hamiltonian\n        \n        # Compute gradient = ⟨ψ|[H,A]|ψ⟩\n        gradient = np.real(state.conj().T @ commutator @ state)\n        gradients.append(gradient)\n    \n    # Find operator with maximum |gradient|\n    abs_gradients = [abs(g) for g in gradients]\n    best_index = np.argmax(abs_gradients)\n    max_gradient = abs_gradients[best_index]\n    \n    return best_index, max_gradient, gradients\n\n# Test\nI = np.eye(2, dtype=complex)\nX = np.array([[0, 1], [1, 0]], dtype=complex)\nY = np.array([[0, -1j], [1j, 0]], dtype=complex)\nZ = np.array([[1, 0], [0, -1]], dtype=complex)\n\nH = np.kron(Z, I) + np.kron(I, Z) + 0.5 * np.kron(X, X)\n\npool = [\n    np.kron(Y, I),\n    np.kron(I, Y),\n    np.kron(Y, X),\n    np.kron(X, Y)\n]\n\npsi = np.array([1, 0, 0, 0], dtype=complex)\n\nbest_idx, max_grad, grads = select_best_operator(H, pool, psi)\nprint(f\"Best operator index: {best_idx}\")\nprint(f\"Maximum gradient: {max_grad:.4f}\")\nprint(f\"All gradients: {[f'{g:.4f}' for g in grads]}\")",
      "hints": [
        "Loop through all operators in the pool",
        "Compute [H, A] = H @ A - A @ H for each",
        "The gradient is the real part of ⟨ψ|[H,A]|ψ⟩",
        "Use abs() to find maximum magnitude, then np.argmax()"
      ],
      "testCases": [
        {
          "input": "Simple 2-qubit test",
          "expected": "Returns index of operator with largest |gradient|"
        }
      ]
    },
    {
      "id": "ex4",
      "title": "Full ADAPT-VQE Iteration",
      "type": "coding",
      "difficulty": "advanced",
      "points": 25,
      "description": "Implement a single ADAPT-VQE iteration: select the best operator, add it to the ansatz, and optimize the new parameter. Track the energy improvement.",
      "starterCode": "import numpy as np\nfrom scipy.linalg import expm\nfrom scipy.optimize import minimize_scalar\n\ndef adapt_vqe_iteration(hamiltonian, pool, current_ops, current_params, ref_state):\n    \"\"\"\n    Perform one ADAPT-VQE iteration.\n    \n    Args:\n        hamiltonian: System Hamiltonian\n        pool: Operator pool\n        current_ops: List of currently selected operators\n        current_params: Current parameter values\n        ref_state: Reference state |ψ₀⟩\n    \n    Returns:\n        dict with:\n        - 'new_ops': Updated operator list\n        - 'new_params': Updated parameters\n        - 'selected_idx': Index of selected operator\n        - 'max_gradient': Maximum gradient found\n        - 'energy_before': Energy before adding operator\n        - 'energy_after': Energy after optimization\n    \"\"\"\n    \n    def build_state(params, ops):\n        \"\"\"Build state from reference by applying exp(θ·A) operators.\"\"\"\n        state = ref_state.copy()\n        for theta, op in zip(params, ops):\n            state = expm(theta * op) @ state\n        return state\n    \n    def compute_energy(state):\n        \"\"\"Compute ⟨ψ|H|ψ⟩.\"\"\"\n        return np.real(state.conj().T @ hamiltonian @ state)\n    \n    # Your code here\n    pass\n\n# Test\nI = np.eye(2, dtype=complex)\nX = np.array([[0, 1], [1, 0]], dtype=complex)\nY = np.array([[0, -1j], [1j, 0]], dtype=complex)\nZ = np.array([[1, 0], [0, -1]], dtype=complex)\n\nH = np.kron(Z, I) + np.kron(I, Z) + 0.5 * np.kron(X, X)\npool = [np.kron(Y, I), np.kron(I, Y), np.kron(Y, X), np.kron(X, Y)]\npsi0 = np.array([1, 0, 0, 0], dtype=complex)\n\nresult = adapt_vqe_iteration(H, pool, [], [], psi0)\nprint(f\"Selected operator: {result['selected_idx']}\")\nprint(f\"Max gradient: {result['max_gradient']:.6f}\")\nprint(f\"Energy before: {result['energy_before']:.6f}\")\nprint(f\"Energy after: {result['energy_after']:.6f}\")",
      "solution": "import numpy as np\nfrom scipy.linalg import expm\nfrom scipy.optimize import minimize_scalar, minimize\n\ndef adapt_vqe_iteration(hamiltonian, pool, current_ops, current_params, ref_state):\n    \"\"\"\n    Perform one ADAPT-VQE iteration.\n    \"\"\"\n    \n    def build_state(params, ops):\n        \"\"\"Build state from reference by applying exp(θ·A) operators.\"\"\"\n        state = ref_state.copy()\n        for theta, op in zip(params, ops):\n            state = expm(theta * op) @ state\n        return state\n    \n    def compute_energy(state):\n        \"\"\"Compute ⟨ψ|H|ψ⟩.\"\"\"\n        return np.real(state.conj().T @ hamiltonian @ state)\n    \n    # Current state and energy\n    current_state = build_state(current_params, current_ops)\n    energy_before = compute_energy(current_state)\n    \n    # Compute gradients for all pool operators\n    gradients = []\n    for op in pool:\n        commutator = hamiltonian @ op - op @ hamiltonian\n        grad = np.real(current_state.conj().T @ commutator @ current_state)\n        gradients.append(grad)\n    \n    # Select best operator\n    abs_grads = [abs(g) for g in gradients]\n    selected_idx = np.argmax(abs_grads)\n    max_gradient = abs_grads[selected_idx]\n    \n    # Add selected operator\n    new_ops = current_ops + [pool[selected_idx]]\n    new_params = list(current_params) + [0.0]\n    \n    # Optimize all parameters\n    def energy_func(params):\n        state = build_state(params, new_ops)\n        return compute_energy(state)\n    \n    result = minimize(energy_func, new_params, method='BFGS')\n    new_params = list(result.x)\n    energy_after = result.fun\n    \n    return {\n        'new_ops': new_ops,\n        'new_params': new_params,\n        'selected_idx': selected_idx,\n        'max_gradient': max_gradient,\n        'energy_before': energy_before,\n        'energy_after': energy_after\n    }\n\n# Test\nI = np.eye(2, dtype=complex)\nX = np.array([[0, 1], [1, 0]], dtype=complex)\nY = np.array([[0, -1j], [1j, 0]], dtype=complex)\nZ = np.array([[1, 0], [0, -1]], dtype=complex)\n\nH = np.kron(Z, I) + np.kron(I, Z) + 0.5 * np.kron(X, X)\npool = [np.kron(Y, I), np.kron(I, Y), np.kron(Y, X), np.kron(X, Y)]\npsi0 = np.array([1, 0, 0, 0], dtype=complex)\n\n# Run multiple iterations\nops, params = [], []\nfor i in range(3):\n    result = adapt_vqe_iteration(H, pool, ops, params, psi0)\n    ops = result['new_ops']\n    params = result['new_params']\n    print(f\"Iteration {i+1}:\")\n    print(f\"  Selected: {result['selected_idx']}, Gradient: {result['max_gradient']:.4f}\")\n    print(f\"  Energy: {result['energy_before']:.6f} → {result['energy_after']:.6f}\")\n\nprint(f\"\\nExact ground state: {np.linalg.eigvalsh(H)[0]:.6f}\")",
      "hints": [
        "Build current state using the existing operators and params",
        "Compute gradient for each pool operator",
        "Select operator with largest |gradient|",
        "Use scipy.optimize.minimize to optimize ALL parameters together"
      ],
      "testCases": [
        {
          "input": "2-qubit test system",
          "expected": "Energy decreases after each iteration"
        }
      ]
    }
  ]
}
