{
  "exerciseId": "07-02-04-continuous-variable-exercises",
  "title": "Exercises: Continuous-Variable QKD",
  "exercises": [
    {
      "id": "ex1",
      "title": "GG02 Protocol Simulator",
      "type": "coding",
      "difficulty": "advanced",
      "points": 30,
      "description": "Build a complete GG02 protocol simulation with parameter estimation.",
      "tasks": [
        "Implement Gaussian random modulation for Alice",
        "Model lossy quantum channel with excess noise",
        "Create homodyne and heterodyne detection modes",
        "Implement parameter estimation from measurement data",
        "Calculate asymptotic key rate"
      ],
      "expectedOutput": "Complete GG02 simulation with security analysis",
      "hints": [
        "Coherent state α = (x + ip)/√2",
        "Channel: α → √η α + noise",
        "Homodyne: measure X or P with shot noise",
        "Key rate: βI(A:B) - χ(B:E)"
      ]
    },
    {
      "id": "ex2",
      "title": "Phase Space Visualizer",
      "type": "coding",
      "difficulty": "intermediate",
      "points": 25,
      "description": "Create interactive phase space visualizations for CV states.",
      "tasks": [
        "Plot coherent state distributions",
        "Visualize Gaussian modulation cloud",
        "Show homodyne projection",
        "Animate channel noise effects",
        "Compare vacuum, thermal, and squeezed states"
      ],
      "expectedOutput": "Interactive phase space visualization tool",
      "hints": [
        "Coherent state: Gaussian centered at α",
        "Vacuum: circular at origin with variance 1",
        "Squeezed: ellipse with ΔX < 1 or ΔP < 1",
        "Use contour plots for probability distributions"
      ]
    },
    {
      "id": "ex3",
      "title": "Noise Budget Calculator",
      "type": "coding",
      "difficulty": "intermediate",
      "points": 20,
      "description": "Calculate and analyze noise contributions in CV-QKD.",
      "tasks": [
        "Model electronic noise from detector",
        "Calculate phase noise from laser linewidth",
        "Estimate channel excess noise",
        "Determine maximum tolerable noise for key generation",
        "Generate system noise budget report"
      ],
      "expectedOutput": "CV-QKD noise analysis tool",
      "hints": [
        "Shot noise = 1 (vacuum units)",
        "Electronic: often quoted in dB below shot noise",
        "Phase noise ∝ linewidth × delay",
        "Total noise determines security threshold"
      ]
    },
    {
      "id": "ex4",
      "title": "CV vs DV Performance Comparison",
      "type": "coding",
      "difficulty": "advanced",
      "points": 25,
      "description": "Compare CV-QKD and DV-QKD performance across scenarios.",
      "tasks": [
        "Model key rates for both approaches",
        "Plot key rate vs distance curves",
        "Analyze crossover points",
        "Compare implementation complexity",
        "Generate protocol selection guide"
      ],
      "expectedOutput": "Comprehensive CV vs DV comparison tool",
      "hints": [
        "CV: high rate, short distance",
        "DV: lower rate, longer distance",
        "Consider detector technology",
        "Metro vs long-haul applications"
      ]
    }
  ]
}
