{
  "id": "04-controlled-unitaries",
  "title": "Controlled Unitaries in QPE",
  "description": "Implementing controlled-U^(2^k) operations efficiently for quantum phase estimation.",
  "order": 4,
  "estimatedMinutes": 40,
  "difficulty": "intermediate",
  "prerequisites": ["03-qpe-analysis"],
  "learningObjectives": [
    "Understand the role of controlled-U^(2^k) in QPE",
    "Implement controlled unitaries using basic gates",
    "Apply repeated squaring for efficient U^(2^k) computation",
    "Handle multi-qubit controlled operations"
  ],
  "tags": ["qpe", "controlled-gates", "unitary", "phase-estimation"],
  "hasQuiz": true,
  "hasExercises": true
}
